{
    "target": {
        "host": "172.16.1.8"
    },
    "credentials": {
        "auth_method": "null",
        "user": "",
        "password": "",
        "domain": "",
        "ticket_file": "",
        "nthash": "",
        "random_user": "rixrosmb"
    },
    "listeners": {
        "LDAP": {
            "port": 389,
            "accessible": false
        },
        "LDAPS": {
            "port": 636,
            "accessible": false
        },
        "SMB": {
            "port": 445,
            "accessible": true
        },
        "SMB over NetBIOS": {
            "port": 139,
            "accessible": true
        }
    },
    "domain": "GFTECH",
    "nmblookup": [
        "GFTECH-MI       <00> -         B <ACTIVE>  Workstation Service",
        "GFTECH          <00> - <GROUP> B <ACTIVE>  Domain/Workgroup Name",
        "GFTECH-MI       <20> -         B <ACTIVE>  File Server Service",
        "GFTECH          <1e> - <GROUP> B <ACTIVE>  Browser Service Elections",
        "MAC Address = C8-D9-D2-0D-07-B9"
    ],
    "smb_dialects": {
        "Supported dialects": {
            "SMB 1.0": false,
            "SMB 2.02": true,
            "SMB 2.1": true,
            "SMB 3.0": true,
            "SMB 3.1.1": true
        },
        "Preferred dialect": "SMB 3.0",
        "SMB1 only": false,
        "SMB signing required": false
    },
    "smb_domain_info": {
        "NetBIOS computer name": "GFTECH-MI",
        "NetBIOS domain name": "GFTECH",
        "DNS domain": "gftech.srl",
        "FQDN": "GFTECH-MI.gftech.srl",
        "Derived membership": "domain member",
        "Derived domain": "GFTECH"
    },
    "sessions": {
        "sessions_possible": false,
        "null": false,
        "password": false,
        "kerberos": false,
        "nthash": false,
        "random_user": false
    },
    "os_info": {
        "OS": "Windows 10, Windows Server 2019, Windows Server 2016",
        "OS version": "10.0",
        "OS release": "2004",
        "OS build": "19041",
        "Native OS": "not supported",
        "Native LAN manager": "not supported",
        "Platform id": null,
        "Server type": null,
        "Server type string": null
    },
    "errors": {
        "listeners": {
            "enum_listeners": [
                "Could not connect to LDAP on 389/tcp: connection refused",
                "Could not connect to LDAPS on 636/tcp: connection refused"
            ]
        },
        "sessions": {
            "enum_sessions": [
                "Could not establish null session: STATUS_ACCESS_DENIED",
                "Could not establish random user session: STATUS_LOGON_FAILURE",
                "Sessions failed, neither null nor user sessions were possible"
            ]
        },
        "os_info": {
            "enum_os_info": [
                "Skipping 'srvinfo' run, not possible with provided credentials"
            ]
        }
    }
}
---
{
    "target": {
        "host": "172.16.1.2"
    },
    "credentials": {
        "auth_method": "null",
        "user": "",
        "password": "",
        "domain": "",
        "ticket_file": "",
        "nthash": "",
        "random_user": "sgfigzga"
    },
    "listeners": {
        "LDAP": {
            "port": 389,
            "accessible": false
        },
        "LDAPS": {
            "port": 636,
            "accessible": false
        },
        "SMB": {
            "port": 445,
            "accessible": true
        },
        "SMB over NetBIOS": {
            "port": 139,
            "accessible": true
        }
    },
    "domain": "GFTECH",
    "nmblookup": [
        "FS02            <00> -         B <ACTIVE>  Workstation Service",
        "FS02            <03> -         B <ACTIVE>  Messenger Service",
        "FS02            <20> -         B <ACTIVE>  File Server Service",
        "..__MSBROWSE__. <01> - <GROUP> B <ACTIVE>  Master Browser",
        "GFTECH          <00> - <GROUP> B <ACTIVE>  Domain/Workgroup Name",
        "GFTECH          <1d> -         B <ACTIVE>  Master Browser",
        "GFTECH          <1e> - <GROUP> B <ACTIVE>  Browser Service Elections",
        "MAC Address = 00-00-00-00-00-00"
    ],
    "smb_dialects": {
        "Supported dialects": {
            "SMB 1.0": false,
            "SMB 2.02": true,
            "SMB 2.1": true,
            "SMB 3.0": true,
            "SMB 3.1.1": true
        },
        "Preferred dialect": "SMB 3.0",
        "SMB1 only": false,
        "SMB signing required": false
    },
    "smb_domain_info": {
        "NetBIOS computer name": "FS02",
        "NetBIOS domain name": "GFTECH",
        "DNS domain": "",
        "FQDN": "localhost",
        "Derived membership": "workgroup member",
        "Derived domain": "unknown"
    },
    "sessions": {
        "sessions_possible": true,
        "null": true,
        "password": false,
        "kerberos": false,
        "nthash": false,
        "random_user": false
    },
    "rpc_domain_info": {
        "Domain": "GFTECH",
        "Domain SID": "S-1-5-21-2857987910-2622034082-2940064511",
        "Membership": "domain member"
    },
    "os_info": {
        "OS": "Linux/Unix (Samba 4.21.2-git.382.df546a2d31bSUSE-oS16.9-x86_)",
        "OS version": "6.1",
        "OS release": "",
        "OS build": "0",
        "Native OS": "not supported",
        "Native LAN manager": "not supported",
        "Platform id": "500",
        "Server type": "0x809b03",
        "Server type string": "Wk Sv Dom PrQ Unx NT SNT Samba 4.21.2-git.382.df546a2d31bSUSE-oS16.9-x86_"
    },
    "users": {},
    "groups": {
        "546": {
            "groupname": "Guests",
            "type": "builtin"
        },
        "544": {
            "groupname": "Administrators",
            "type": "builtin"
        },
        "545": {
            "groupname": "Users",
            "type": "builtin"
        }
    },
    "shares": {
        "amministrazione": {
            "type": "Disk",
            "comment": "Amministrazione GFTech",
            "access": {
                "mapping": "denied",
                "listing": "n/a"
            }
        },
        "commerciale": {
            "type": "Disk",
            "comment": "Commerciale GFTech",
            "access": {
                "mapping": "denied",
                "listing": "n/a"
            }
        },
        "personale": {
            "type": "Disk",
            "comment": "Personale GFTech",
            "access": {
                "mapping": "denied",
                "listing": "n/a"
            }
        },
        "varie": {
            "type": "Disk",
            "comment": "Varie GFTech",
            "access": {
                "mapping": "denied",
                "listing": "n/a"
            }
        },
        "scansioni": {
            "type": "Disk",
            "comment": "Varie GFTech",
            "access": {
                "mapping": "denied",
                "listing": "n/a"
            }
        },
        "tecnici": {
            "type": "Disk",
            "comment": "Tecnici GFTech",
            "access": {
                "mapping": "denied",
                "listing": "n/a"
            }
        },
        "IPC$": {
            "type": "IPC",
            "comment": "IPC Service (Samba 4.21.2-git.382.df546a2d31bSUSE-oS16.9-x86_64)",
            "access": {
                "mapping": "ok",
                "listing": "not supported"
            }
        }
    },
    "policy": {
        "Domain password information": {
            "Password history length": "None",
            "Minimum password length": 5,
            "Maximum password age": "49710 days 6 hours 21 minutes",
            "Password properties": [
                {
                    "DOMAIN_PASSWORD_COMPLEX": false
                },
                {
                    "DOMAIN_PASSWORD_NO_ANON_CHANGE": false
                },
                {
                    "DOMAIN_PASSWORD_NO_CLEAR_CHANGE": false
                },
                {
                    "DOMAIN_PASSWORD_LOCKOUT_ADMINS": false
                },
                {
                    "DOMAIN_PASSWORD_PASSWORD_STORE_CLEARTEXT": false
                },
                {
                    "DOMAIN_PASSWORD_REFUSE_PASSWORD_CHANGE": false
                }
            ]
        },
        "Domain lockout information": {
            "Lockout observation window": "30 minutes",
            "Lockout duration": "30 minutes",
            "Lockout threshold": "None"
        },
        "Domain logoff information": {
            "Force logoff time": "49710 days 6 hours 21 minutes"
        }
    },
    "printers": {},
    "errors": {
        "listeners": {
            "enum_listeners": [
                "Could not connect to LDAP on 389/tcp: connection refused",
                "Could not connect to LDAPS on 636/tcp: connection refused"
            ]
        },
        "sessions": {
            "enum_sessions": [
                "Could not establish random user session: STATUS_LOGON_FAILURE"
            ]
        }
    }
}
---
{
    "target": {
        "host": "172.16.1.44"
    },
    "credentials": {
        "auth_method": "null",
        "user": "",
        "password": "",
        "domain": "",
        "ticket_file": "",
        "nthash": "",
        "random_user": "lbosojia"
    },
    "listeners": {
        "LDAP": {
            "port": 389,
            "accessible": false
        },
        "LDAPS": {
            "port": 636,
            "accessible": false
        },
        "SMB": {
            "port": 445,
            "accessible": true
        },
        "SMB over NetBIOS": {
            "port": 139,
            "accessible": true
        }
    },
    "domain": "GFTECH",
    "nmblookup": [
        "GFTECH          <00> - <GROUP> B <ACTIVE>  Domain/Workgroup Name",
        "GF-TEO-OFFICE   <00> -         B <ACTIVE>  Workstation Service",
        "GF-TEO-OFFICE   <20> -         B <ACTIVE>  File Server Service",
        "MAC Address = 9C-7B-EF-28-54-4E"
    ],
    "smb_dialects": {
        "Supported dialects": {
            "SMB 1.0": false,
            "SMB 2.02": true,
            "SMB 2.1": true,
            "SMB 3.0": true,
            "SMB 3.1.1": true
        },
        "Preferred dialect": "SMB 3.0",
        "SMB1 only": false,
        "SMB signing required": false
    },
    "smb_domain_info": {
        "NetBIOS computer name": "GF-TEO-OFFICE",
        "NetBIOS domain name": "GFTECH",
        "DNS domain": "gftech.srl",
        "FQDN": "GF-TEO-OFFICE.gftech.srl",
        "Derived membership": "domain member",
        "Derived domain": "GFTECH"
    },
    "sessions": {
        "sessions_possible": false,
        "null": false,
        "password": false,
        "kerberos": false,
        "nthash": false,
        "random_user": false
    },
    "os_info": {
        "OS": "Windows 10, Windows Server 2019, Windows Server 2016",
        "OS version": "10.0",
        "OS release": "2004",
        "OS build": "19041",
        "Native OS": "not supported",
        "Native LAN manager": "not supported",
        "Platform id": null,
        "Server type": null,
        "Server type string": null
    },
    "errors": {
        "listeners": {
            "enum_listeners": [
                "Could not connect to LDAP on 389/tcp: timed out",
                "Could not connect to LDAPS on 636/tcp: timed out"
            ]
        },
        "sessions": {
            "enum_sessions": [
                "Could not establish null session: STATUS_ACCESS_DENIED",
                "Could not establish random user session: STATUS_LOGON_FAILURE",
                "Sessions failed, neither null nor user sessions were possible"
            ]
        },
        "os_info": {
            "enum_os_info": [
                "Skipping 'srvinfo' run, not possible with provided credentials"
            ]
        }
    }
}
---
{
    "target": {
        "host": "172.16.1.32"
    },
    "credentials": {
        "auth_method": "null",
        "user": "",
        "password": "",
        "domain": "",
        "ticket_file": "",
        "nthash": "",
        "random_user": "wosgubxe"
    },
    "listeners": {
        "LDAP": {
            "port": 389,
            "accessible": false
        },
        "LDAPS": {
            "port": 636,
            "accessible": false
        },
        "SMB": {
            "port": 445,
            "accessible": true
        },
        "SMB over NetBIOS": {
            "port": 139,
            "accessible": true
        }
    },
    "domain": "GFTECH",
    "nmblookup": [
        "SARA-PC         <20> -         M <ACTIVE>  File Server Service",
        "SARA-PC         <00> -         M <ACTIVE>  Workstation Service",
        "GFTECH          <00> - <GROUP> M <ACTIVE>  Domain/Workgroup Name",
        "MAC Address = 38-CA-84-44-5E-58"
    ],
    "smb_dialects": {
        "Supported dialects": {
            "SMB 1.0": false,
            "SMB 2.02": true,
            "SMB 2.1": true,
            "SMB 3.0": true,
            "SMB 3.1.1": true
        },
        "Preferred dialect": "SMB 3.0",
        "SMB1 only": false,
        "SMB signing required": false
    },
    "smb_domain_info": {
        "NetBIOS computer name": "SARA-PC",
        "NetBIOS domain name": "GFTECH",
        "DNS domain": "gftech.srl",
        "FQDN": "sara-pc.gftech.srl",
        "Derived membership": "domain member",
        "Derived domain": "GFTECH"
    },
    "sessions": {
        "sessions_possible": false,
        "null": false,
        "password": false,
        "kerberos": false,
        "nthash": false,
        "random_user": false
    },
    "os_info": {
        "OS": "Windows 10, Windows Server 2019, Windows Server 2016",
        "OS version": "10.0",
        "OS release": "",
        "OS build": "22621",
        "Native OS": "not supported",
        "Native LAN manager": "not supported",
        "Platform id": null,
        "Server type": null,
        "Server type string": null
    },
    "errors": {
        "listeners": {
            "enum_listeners": [
                "Could not connect to LDAP on 389/tcp: timed out",
                "Could not connect to LDAPS on 636/tcp: timed out"
            ]
        },
        "sessions": {
            "enum_sessions": [
                "Could not establish null session: STATUS_ACCESS_DENIED",
                "Could not establish random user session: STATUS_LOGON_FAILURE",
                "Sessions failed, neither null nor user sessions were possible"
            ]
        },
        "os_info": {
            "enum_os_info": [
                "Skipping 'srvinfo' run, not possible with provided credentials"
            ]
        }
    }
}
---
{
    "target": {
        "host": "172.16.1.77"
    },
    "credentials": {
        "auth_method": "null",
        "user": "",
        "password": "",
        "domain": "",
        "ticket_file": "",
        "nthash": "",
        "random_user": "pecsuxxa"
    },
    "listeners": {
        "LDAP": {
            "port": 389,
            "accessible": false
        },
        "LDAPS": {
            "port": 636,
            "accessible": false
        },
        "SMB": {
            "port": 445,
            "accessible": true
        },
        "SMB over NetBIOS": {
            "port": 139,
            "accessible": true
        }
    },
    "domain": "WORKGROUP",
    "nmblookup": [
        "GF-NAS          <00> -         B <ACTIVE>  Workstation Service",
        "GF-NAS          <03> -         B <ACTIVE>  Messenger Service",
        "GF-NAS          <20> -         B <ACTIVE>  File Server Service",
        "WORKGROUP       <00> - <GROUP> B <ACTIVE>  Domain/Workgroup Name",
        "WORKGROUP       <1e> - <GROUP> B <ACTIVE>  Browser Service Elections",
        "MAC Address = 00-00-00-00-00-00"
    ],
    "smb_dialects": {
        "Supported dialects": {
            "SMB 1.0": false,
            "SMB 2.02": true,
            "SMB 2.1": true,
            "SMB 3.0": true,
            "SMB 3.1.1": true
        },
        "Preferred dialect": "SMB 3.0",
        "SMB1 only": false,
        "SMB signing required": false
    },
    "smb_domain_info": {
        "NetBIOS computer name": "GF-NAS",
        "NetBIOS domain name": "",
        "DNS domain": "",
        "FQDN": "gf-nas",
        "Derived membership": "workgroup member",
        "Derived domain": "unknown"
    },
    "sessions": {
        "sessions_possible": false,
        "null": false,
        "password": false,
        "kerberos": false,
        "nthash": false,
        "random_user": false
    },
    "os_info": {
        "OS": "Windows 7, Windows Server 2008 R2",
        "OS version": "6.1",
        "OS release": "",
        "OS build": "0",
        "Native OS": "not supported",
        "Native LAN manager": "not supported",
        "Platform id": null,
        "Server type": null,
        "Server type string": null
    },
    "errors": {
        "listeners": {
            "enum_listeners": [
                "Could not connect to LDAP on 389/tcp: connection refused",
                "Could not connect to LDAPS on 636/tcp: connection refused"
            ]
        },
        "sessions": {
            "enum_sessions": [
                "Could not establish null session: STATUS_ACCESS_DENIED",
                "Could not establish random user session: STATUS_LOGON_FAILURE",
                "Sessions failed, neither null nor user sessions were possible"
            ]
        },
        "os_info": {
            "enum_os_info": [
                "Skipping 'srvinfo' run, not possible with provided credentials"
            ]
        }
    }
}
---
{
    "target": {
        "host": "172.16.1.31"
    },
    "credentials": {
        "auth_method": "null",
        "user": "",
        "password": "",
        "domain": "",
        "ticket_file": "",
        "nthash": "",
        "random_user": "upkxcdqf"
    },
    "listeners": {
        "LDAP": {
            "port": 389,
            "accessible": false
        },
        "LDAPS": {
            "port": 636,
            "accessible": false
        },
        "SMB": {
            "port": 445,
            "accessible": true
        },
        "SMB over NetBIOS": {
            "port": 139,
            "accessible": true
        }
    },
    "domain": "WORKGROUP",
    "nmblookup": [
        "GFTECH-NB-CA    <20> -         M <ACTIVE>  File Server Service",
        "GFTECH-NB-CA    <00> -         M <ACTIVE>  Workstation Service",
        "WORKGROUP       <00> - <GROUP> M <ACTIVE>  Domain/Workgroup Name",
        "MAC Address = 60-18-95-49-AA-A6"
    ],
    "smb_dialects": {
        "Supported dialects": {
            "SMB 1.0": false,
            "SMB 2.02": true,
            "SMB 2.1": true,
            "SMB 3.0": true,
            "SMB 3.1.1": true
        },
        "Preferred dialect": "SMB 3.0",
        "SMB1 only": false,
        "SMB signing required": false
    },
    "smb_domain_info": {
        "NetBIOS computer name": "GFTECH-NB-CA",
        "NetBIOS domain name": "",
        "DNS domain": "GFtech-NB-CA",
        "FQDN": "GFtech-NB-CA",
        "Derived membership": "workgroup member",
        "Derived domain": "unknown"
    },
    "sessions": {
        "sessions_possible": false,
        "null": false,
        "password": false,
        "kerberos": false,
        "nthash": false,
        "random_user": false
    },
    "os_info": {
        "OS": "Windows 10, Windows Server 2019, Windows Server 2016",
        "OS version": "10.0",
        "OS release": "2004",
        "OS build": "19041",
        "Native OS": "not supported",
        "Native LAN manager": "not supported",
        "Platform id": null,
        "Server type": null,
        "Server type string": null
    },
    "errors": {
        "listeners": {
            "enum_listeners": [
                "Could not connect to LDAP on 389/tcp: connection refused",
                "Could not connect to LDAPS on 636/tcp: connection refused"
            ]
        },
        "sessions": {
            "enum_sessions": [
                "Could not establish null session: STATUS_ACCESS_DENIED",
                "Could not establish random user session: STATUS_LOGON_FAILURE",
                "Sessions failed, neither null nor user sessions were possible"
            ]
        },
        "os_info": {
            "enum_os_info": [
                "Skipping 'srvinfo' run, not possible with provided credentials"
            ]
        }
    }
}
---
{
    "target": {
        "host": "172.16.1.94"
    },
    "credentials": {
        "auth_method": "null",
        "user": "",
        "password": "",
        "domain": "",
        "ticket_file": "",
        "nthash": "",
        "random_user": "mjelqulz"
    },
    "listeners": {
        "LDAP": {
            "port": 389,
            "accessible": false
        },
        "LDAPS": {
            "port": 636,
            "accessible": false
        },
        "SMB": {
            "port": 445,
            "accessible": false
        },
        "SMB over NetBIOS": {
            "port": 139,
            "accessible": true
        }
    },
    "domain": null,
    "nmblookup": null,
    "smb_dialects": null,
    "smb_domain_info": null,
    "sessions": {
        "sessions_possible": false,
        "null": false,
        "password": false,
        "kerberos": false,
        "nthash": false,
        "random_user": false
    },
    "os_info": null,
    "errors": {
        "listeners": {
            "enum_listeners": [
                "Could not connect to LDAP on 389/tcp: timed out",
                "Could not connect to LDAPS on 636/tcp: timed out",
                "Could not connect to SMB on 445/tcp: timed out"
            ]
        },
        "nmblookup": {
            "enum_netbios": [
                "Could not get NetBIOS names information via 'nmblookup': host does not reply"
            ]
        },
        "domain": {
            "enum_netbios": [
                "Could not get NetBIOS names information via 'nmblookup': host does not reply"
            ]
        },
        "smb1_only": {
            "enum_smb": [
                "No supported dialects found"
            ]
        },
        "smb_domain_info": {
            "enum_smb_domain_info": [
                "SMB connection error on port 139/tcp: session failed"
            ]
        },
        "sessions": {
            "enum_sessions": [
                "Could not establish null session: STATUS_ACCESS_DENIED",
                "Could not establish random user session: STATUS_INVALID_PARAMETER",
                "Sessions failed, neither null nor user sessions were possible"
            ]
        },
        "os_info": {
            "enum_os_info": [
                "SMB connection error on port 139/tcp: session failed",
                "Skipping 'srvinfo' run, not possible with provided credentials"
            ]
        }
    }
}
---
{
    "target": {
        "host": "172.16.1.110"
    },
    "credentials": {
        "auth_method": "null",
        "user": "",
        "password": "",
        "domain": "",
        "ticket_file": "",
        "nthash": "",
        "random_user": "ymeuvkrm"
    },
    "listeners": {
        "LDAP": {
            "port": 389,
            "accessible": false
        },
        "LDAPS": {
            "port": 636,
            "accessible": false
        },
        "SMB": {
            "port": 445,
            "accessible": true
        },
        "SMB over NetBIOS": {
            "port": 139,
            "accessible": true
        }
    },
    "domain": "GFTECH",
    "nmblookup": [
        "GF-CIUCHINO     <00> -         M <ACTIVE>  Workstation Service",
        "GFTECH          <00> - <GROUP> M <ACTIVE>  Domain/Workgroup Name",
        "GF-CIUCHINO     <20> -         M <ACTIVE>  File Server Service",
        "MAC Address = 00-68-EB-AF-A8-40"
    ],
    "smb_dialects": {
        "Supported dialects": {
            "SMB 1.0": false,
            "SMB 2.02": true,
            "SMB 2.1": true,
            "SMB 3.0": true,
            "SMB 3.1.1": true
        },
        "Preferred dialect": "SMB 3.0",
        "SMB1 only": false,
        "SMB signing required": false
    },
    "smb_domain_info": {
        "NetBIOS computer name": "GF-CIUCHINO",
        "NetBIOS domain name": "GFTECH",
        "DNS domain": "gftech.srl",
        "FQDN": "GF-ciuchino.gftech.srl",
        "Derived membership": "domain member",
        "Derived domain": "GFTECH"
    },
    "sessions": {
        "sessions_possible": false,
        "null": false,
        "password": false,
        "kerberos": false,
        "nthash": false,
        "random_user": false
    },
    "os_info": {
        "OS": "Windows 10, Windows Server 2019, Windows Server 2016",
        "OS version": "10.0",
        "OS release": "2004",
        "OS build": "19041",
        "Native OS": "not supported",
        "Native LAN manager": "not supported",
        "Platform id": null,
        "Server type": null,
        "Server type string": null
    },
    "errors": {
        "listeners": {
            "enum_listeners": [
                "Could not connect to LDAP on 389/tcp: connection refused",
                "Could not connect to LDAPS on 636/tcp: connection refused"
            ]
        },
        "sessions": {
            "enum_sessions": [
                "Could not establish null session: STATUS_ACCESS_DENIED",
                "Could not establish random user session: STATUS_LOGON_FAILURE",
                "Sessions failed, neither null nor user sessions were possible"
            ]
        },
        "os_info": {
            "enum_os_info": [
                "Skipping 'srvinfo' run, not possible with provided credentials"
            ]
        }
    }
}
---
{
    "target": {
        "host": "172.16.1.3"
    },
    "credentials": {
        "auth_method": "null",
        "user": "",
        "password": "",
        "domain": "",
        "ticket_file": "",
        "nthash": "",
        "random_user": "aorvezlw"
    },
    "listeners": {
        "LDAP": {
            "port": 389,
            "accessible": true
        },
        "LDAPS": {
            "port": 636,
            "accessible": true
        },
        "SMB": {
            "port": 445,
            "accessible": true
        },
        "SMB over NetBIOS": {
            "port": 139,
            "accessible": true
        }
    },
    "is_parent_dc": true,
    "is_child_dc": false,
    "long_domain": "gftech.srl",
    "domain": "GFTECH",
    "nmblookup": [
        "GFTECH          <00> - <GROUP> B <ACTIVE>  Domain/Workgroup Name",
        "DC01            <00> -         B <ACTIVE>  Workstation Service",
        "GFTECH          <1c> - <GROUP> B <ACTIVE>  Domain Controllers",
        "DC01            <20> -         B <ACTIVE>  File Server Service",
        "GFTECH          <1b> -         B <ACTIVE>  Domain Master Browser",
        "MAC Address = 00-0C-29-8D-46-02"
    ],
    "smb_dialects": {
        "Supported dialects": {
            "SMB 1.0": true,
            "SMB 2.02": true,
            "SMB 2.1": true,
            "SMB 3.0": true,
            "SMB 3.1.1": true
        },
        "Preferred dialect": "SMB 3.0",
        "SMB1 only": false,
        "SMB signing required": true
    },
    "smb_domain_info": {
        "NetBIOS computer name": "DC01",
        "NetBIOS domain name": "GFTECH",
        "DNS domain": "gftech.srl",
        "FQDN": "DC01.gftech.srl",
        "Derived membership": "domain member",
        "Derived domain": "GFTECH"
    },
    "sessions": {
        "sessions_possible": false,
        "null": false,
        "password": false,
        "kerberos": false,
        "nthash": false,
        "random_user": false
    },
    "os_info": {
        "OS": "Windows Server 2016 Standard 14393",
        "OS version": "10.0",
        "OS release": "1607",
        "OS build": "14393",
        "Native OS": "Windows Server 2016 Standard 14393",
        "Native LAN manager": "Windows Server 2016 Standard 6.3",
        "Platform id": null,
        "Server type": null,
        "Server type string": null
    },
    "errors": {
        "sessions": {
            "enum_sessions": [
                "Could not establish null session: STATUS_ACCESS_DENIED",
                "Could not establish random user session: STATUS_LOGON_FAILURE",
                "Sessions failed, neither null nor user sessions were possible"
            ]
        },
        "os_info": {
            "enum_os_info": [
                "Skipping 'srvinfo' run, not possible with provided credentials"
            ]
        }
    }
}
---
{
    "target": {
        "host": "172.16.1.159"
    },
    "credentials": {
        "auth_method": "null",
        "user": "",
        "password": "",
        "domain": "",
        "ticket_file": "",
        "nthash": "",
        "random_user": "kohcmgtg"
    },
    "listeners": {
        "LDAP": {
            "port": 389,
            "accessible": false
        },
        "LDAPS": {
            "port": 636,
            "accessible": false
        },
        "SMB": {
            "port": 445,
            "accessible": true
        },
        "SMB over NetBIOS": {
            "port": 139,
            "accessible": true
        }
    },
    "domain": "GFTECH",
    "nmblookup": [
        "GFTECH-AP       <20> -         M <ACTIVE>  File Server Service",
        "GFTECH-AP       <00> -         M <ACTIVE>  Workstation Service",
        "GFTECH          <00> - <GROUP> M <ACTIVE>  Domain/Workgroup Name",
        "MAC Address = 34-29-8F-10-64-E9"
    ],
    "smb_dialects": {
        "Supported dialects": {
            "SMB 1.0": false,
            "SMB 2.02": true,
            "SMB 2.1": true,
            "SMB 3.0": true,
            "SMB 3.1.1": true
        },
        "Preferred dialect": "SMB 3.0",
        "SMB1 only": false,
        "SMB signing required": false
    },
    "smb_domain_info": {
        "NetBIOS computer name": "GFTECH-AP",
        "NetBIOS domain name": "GFTECH",
        "DNS domain": "gftech.srl",
        "FQDN": "GFTECH-AP.gftech.srl",
        "Derived membership": "domain member",
        "Derived domain": "GFTECH"
    },
    "sessions": {
        "sessions_possible": false,
        "null": false,
        "password": false,
        "kerberos": false,
        "nthash": false,
        "random_user": false
    },
    "os_info": {
        "OS": "Windows 10, Windows Server 2019, Windows Server 2016",
        "OS version": "10.0",
        "OS release": "",
        "OS build": "22621",
        "Native OS": "not supported",
        "Native LAN manager": "not supported",
        "Platform id": null,
        "Server type": null,
        "Server type string": null
    },
    "errors": {
        "listeners": {
            "enum_listeners": [
                "Could not connect to LDAP on 389/tcp: timed out",
                "Could not connect to LDAPS on 636/tcp: timed out"
            ]
        },
        "sessions": {
            "enum_sessions": [
                "Could not establish null session: STATUS_ACCESS_DENIED",
                "Could not establish random user session: STATUS_LOGON_FAILURE",
                "Sessions failed, neither null nor user sessions were possible"
            ]
        },
        "os_info": {
            "enum_os_info": [
                "Skipping 'srvinfo' run, not possible with provided credentials"
            ]
        }
    }
}
---
{
    "target": {
        "host": "172.16.1.131"
    },
    "credentials": {
        "auth_method": "null",
        "user": "",
        "password": "",
        "domain": "",
        "ticket_file": "",
        "nthash": "",
        "random_user": "nfrvvesx"
    },
    "listeners": {
        "LDAP": {
            "port": 389,
            "accessible": false
        },
        "LDAPS": {
            "port": 636,
            "accessible": false
        },
        "SMB": {
            "port": 445,
            "accessible": false
        },
        "SMB over NetBIOS": {
            "port": 139,
            "accessible": false
        }
    },
    "domain": null,
    "nmblookup": [
        "MACBOOKAIR-E8D9 <00> -         H <ACTIVE>  Workstation Service",
        "MAC Address = FE-00-71-42-6E-D5"
    ],
    "errors": {
        "listeners": {
            "enum_listeners": [
                "Could not connect to LDAP on 389/tcp: connection refused",
                "Could not connect to LDAPS on 636/tcp: connection refused",
                "Could not connect to SMB on 445/tcp: connection refused",
                "Could not connect to SMB over NetBIOS on 139/tcp: connection refused"
            ]
        },
        "domain": {
            "enum_netbios": [
                "Could not find domain/domain"
            ]
        }
    }
}
---
{
    "target": {
        "host": "172.16.1.8"
    },
    "credentials": {
        "auth_method": "null",
        "user": "",
        "password": "",
        "domain": "",
        "ticket_file": "",
        "nthash": "",
        "random_user": "gfsktfzs"
    },
    "listeners": {
        "LDAP": {
            "port": 389,
            "accessible": false
        },
        "LDAPS": {
            "port": 636,
            "accessible": false
        },
        "SMB": {
            "port": 445,
            "accessible": true
        },
        "SMB over NetBIOS": {
            "port": 139,
            "accessible": true
        }
    },
    "domain": "GFTECH",
    "nmblookup": [
        "GFTECH-MI       <00> -         B <ACTIVE>  Workstation Service",
        "GFTECH          <00> - <GROUP> B <ACTIVE>  Domain/Workgroup Name",
        "GFTECH-MI       <20> -         B <ACTIVE>  File Server Service",
        "GFTECH          <1e> - <GROUP> B <ACTIVE>  Browser Service Elections",
        "MAC Address = C8-D9-D2-0D-07-B9"
    ],
    "smb_dialects": {
        "Supported dialects": {
            "SMB 1.0": false,
            "SMB 2.02": true,
            "SMB 2.1": true,
            "SMB 3.0": true,
            "SMB 3.1.1": true
        },
        "Preferred dialect": "SMB 3.0",
        "SMB1 only": false,
        "SMB signing required": false
    },
    "smb_domain_info": {
        "NetBIOS computer name": "GFTECH-MI",
        "NetBIOS domain name": "GFTECH",
        "DNS domain": "gftech.srl",
        "FQDN": "GFTECH-MI.gftech.srl",
        "Derived membership": "domain member",
        "Derived domain": "GFTECH"
    },
    "sessions": {
        "sessions_possible": false,
        "null": false,
        "password": false,
        "kerberos": false,
        "nthash": false,
        "random_user": false
    },
    "os_info": {
        "OS": "Windows 10, Windows Server 2019, Windows Server 2016",
        "OS version": "10.0",
        "OS release": "2004",
        "OS build": "19041",
        "Native OS": "not supported",
        "Native LAN manager": "not supported",
        "Platform id": null,
        "Server type": null,
        "Server type string": null
    },
    "errors": {
        "listeners": {
            "enum_listeners": [
                "Could not connect to LDAP on 389/tcp: connection refused",
                "Could not connect to LDAPS on 636/tcp: connection refused"
            ]
        },
        "sessions": {
            "enum_sessions": [
                "Could not establish null session: STATUS_ACCESS_DENIED",
                "Could not establish random user session: STATUS_LOGON_FAILURE",
                "Sessions failed, neither null nor user sessions were possible"
            ]
        },
        "os_info": {
            "enum_os_info": [
                "Skipping 'srvinfo' run, not possible with provided credentials"
            ]
        }
    }
}
---
{
    "target": {
        "host": "172.16.1.2"
    },
    "credentials": {
        "auth_method": "null",
        "user": "",
        "password": "",
        "domain": "",
        "ticket_file": "",
        "nthash": "",
        "random_user": "vmvgchqq"
    },
    "listeners": {
        "LDAP": {
            "port": 389,
            "accessible": false
        },
        "LDAPS": {
            "port": 636,
            "accessible": false
        },
        "SMB": {
            "port": 445,
            "accessible": true
        },
        "SMB over NetBIOS": {
            "port": 139,
            "accessible": true
        }
    },
    "domain": "GFTECH",
    "nmblookup": [
        "FS02            <00> -         B <ACTIVE>  Workstation Service",
        "FS02            <03> -         B <ACTIVE>  Messenger Service",
        "FS02            <20> -         B <ACTIVE>  File Server Service",
        "..__MSBROWSE__. <01> - <GROUP> B <ACTIVE>  Master Browser",
        "GFTECH          <00> - <GROUP> B <ACTIVE>  Domain/Workgroup Name",
        "GFTECH          <1d> -         B <ACTIVE>  Master Browser",
        "GFTECH          <1e> - <GROUP> B <ACTIVE>  Browser Service Elections",
        "MAC Address = 00-00-00-00-00-00"
    ],
    "smb_dialects": {
        "Supported dialects": {
            "SMB 1.0": false,
            "SMB 2.02": true,
            "SMB 2.1": true,
            "SMB 3.0": true,
            "SMB 3.1.1": true
        },
        "Preferred dialect": "SMB 3.0",
        "SMB1 only": false,
        "SMB signing required": false
    },
    "smb_domain_info": {
        "NetBIOS computer name": "FS02",
        "NetBIOS domain name": "GFTECH",
        "DNS domain": "",
        "FQDN": "localhost",
        "Derived membership": "workgroup member",
        "Derived domain": "unknown"
    },
    "sessions": {
        "sessions_possible": true,
        "null": true,
        "password": false,
        "kerberos": false,
        "nthash": false,
        "random_user": false
    },
    "rpc_domain_info": {
        "Domain": "GFTECH",
        "Domain SID": "S-1-5-21-2857987910-2622034082-2940064511",
        "Membership": "domain member"
    },
    "os_info": {
        "OS": "Linux/Unix (Samba 4.21.2-git.382.df546a2d31bSUSE-oS16.9-x86_)",
        "OS version": "6.1",
        "OS release": "",
        "OS build": "0",
        "Native OS": "not supported",
        "Native LAN manager": "not supported",
        "Platform id": "500",
        "Server type": "0x809b03",
        "Server type string": "Wk Sv Dom PrQ Unx NT SNT Samba 4.21.2-git.382.df546a2d31bSUSE-oS16.9-x86_"
    },
    "users": {},
    "groups": {
        "546": {
            "groupname": "Guests",
            "type": "builtin"
        },
        "544": {
            "groupname": "Administrators",
            "type": "builtin"
        },
        "545": {
            "groupname": "Users",
            "type": "builtin"
        }
    },
    "shares": {
        "amministrazione": {
            "type": "Disk",
            "comment": "Amministrazione GFTech",
            "access": {
                "mapping": "denied",
                "listing": "n/a"
            }
        },
        "commerciale": {
            "type": "Disk",
            "comment": "Commerciale GFTech",
            "access": {
                "mapping": "denied",
                "listing": "n/a"
            }
        },
        "personale": {
            "type": "Disk",
            "comment": "Personale GFTech",
            "access": {
                "mapping": "denied",
                "listing": "n/a"
            }
        },
        "varie": {
            "type": "Disk",
            "comment": "Varie GFTech",
            "access": {
                "mapping": "denied",
                "listing": "n/a"
            }
        },
        "scansioni": {
            "type": "Disk",
            "comment": "Varie GFTech",
            "access": {
                "mapping": "denied",
                "listing": "n/a"
            }
        },
        "tecnici": {
            "type": "Disk",
            "comment": "Tecnici GFTech",
            "access": {
                "mapping": "denied",
                "listing": "n/a"
            }
        },
        "IPC$": {
            "type": "IPC",
            "comment": "IPC Service (Samba 4.21.2-git.382.df546a2d31bSUSE-oS16.9-x86_64)",
            "access": {
                "mapping": "ok",
                "listing": "not supported"
            }
        }
    },
    "policy": {
        "Domain password information": {
            "Password history length": "None",
            "Minimum password length": 5,
            "Maximum password age": "49710 days 6 hours 21 minutes",
            "Password properties": [
                {
                    "DOMAIN_PASSWORD_COMPLEX": false
                },
                {
                    "DOMAIN_PASSWORD_NO_ANON_CHANGE": false
                },
                {
                    "DOMAIN_PASSWORD_NO_CLEAR_CHANGE": false
                },
                {
                    "DOMAIN_PASSWORD_LOCKOUT_ADMINS": false
                },
                {
                    "DOMAIN_PASSWORD_PASSWORD_STORE_CLEARTEXT": false
                },
                {
                    "DOMAIN_PASSWORD_REFUSE_PASSWORD_CHANGE": false
                }
            ]
        },
        "Domain lockout information": {
            "Lockout observation window": "30 minutes",
            "Lockout duration": "30 minutes",
            "Lockout threshold": "None"
        },
        "Domain logoff information": {
            "Force logoff time": "49710 days 6 hours 21 minutes"
        }
    },
    "printers": {},
    "errors": {
        "listeners": {
            "enum_listeners": [
                "Could not connect to LDAP on 389/tcp: connection refused",
                "Could not connect to LDAPS on 636/tcp: connection refused"
            ]
        },
        "sessions": {
            "enum_sessions": [
                "Could not establish random user session: STATUS_LOGON_FAILURE"
            ]
        }
    }
}
---
{
    "target": {
        "host": "172.16.1.44"
    },
    "credentials": {
        "auth_method": "null",
        "user": "",
        "password": "",
        "domain": "",
        "ticket_file": "",
        "nthash": "",
        "random_user": "gtfsnqxq"
    },
    "listeners": {
        "LDAP": {
            "port": 389,
            "accessible": false
        },
        "LDAPS": {
            "port": 636,
            "accessible": false
        },
        "SMB": {
            "port": 445,
            "accessible": true
        },
        "SMB over NetBIOS": {
            "port": 139,
            "accessible": true
        }
    },
    "domain": "GFTECH",
    "nmblookup": [
        "GFTECH          <00> - <GROUP> B <ACTIVE>  Domain/Workgroup Name",
        "GF-TEO-OFFICE   <00> -         B <ACTIVE>  Workstation Service",
        "GF-TEO-OFFICE   <20> -         B <ACTIVE>  File Server Service",
        "MAC Address = 9C-7B-EF-28-54-4E"
    ],
    "smb_dialects": {
        "Supported dialects": {
            "SMB 1.0": false,
            "SMB 2.02": true,
            "SMB 2.1": true,
            "SMB 3.0": true,
            "SMB 3.1.1": true
        },
        "Preferred dialect": "SMB 3.0",
        "SMB1 only": false,
        "SMB signing required": false
    },
    "smb_domain_info": {
        "NetBIOS computer name": "GF-TEO-OFFICE",
        "NetBIOS domain name": "GFTECH",
        "DNS domain": "gftech.srl",
        "FQDN": "GF-TEO-OFFICE.gftech.srl",
        "Derived membership": "domain member",
        "Derived domain": "GFTECH"
    },
    "sessions": {
        "sessions_possible": false,
        "null": false,
        "password": false,
        "kerberos": false,
        "nthash": false,
        "random_user": false
    },
    "os_info": {
        "OS": "Windows 10, Windows Server 2019, Windows Server 2016",
        "OS version": "10.0",
        "OS release": "2004",
        "OS build": "19041",
        "Native OS": "not supported",
        "Native LAN manager": "not supported",
        "Platform id": null,
        "Server type": null,
        "Server type string": null
    },
    "errors": {
        "listeners": {
            "enum_listeners": [
                "Could not connect to LDAP on 389/tcp: timed out",
                "Could not connect to LDAPS on 636/tcp: timed out"
            ]
        },
        "sessions": {
            "enum_sessions": [
                "Could not establish null session: STATUS_ACCESS_DENIED",
                "Could not establish random user session: STATUS_LOGON_FAILURE",
                "Sessions failed, neither null nor user sessions were possible"
            ]
        },
        "os_info": {
            "enum_os_info": [
                "Skipping 'srvinfo' run, not possible with provided credentials"
            ]
        }
    }
}
---
{
    "target": {
        "host": "172.16.1.32"
    },
    "credentials": {
        "auth_method": "null",
        "user": "",
        "password": "",
        "domain": "",
        "ticket_file": "",
        "nthash": "",
        "random_user": "zlzfewlp"
    },
    "listeners": {
        "LDAP": {
            "port": 389,
            "accessible": false
        },
        "LDAPS": {
            "port": 636,
            "accessible": false
        },
        "SMB": {
            "port": 445,
            "accessible": true
        },
        "SMB over NetBIOS": {
            "port": 139,
            "accessible": true
        }
    },
    "domain": "GFTECH",
    "nmblookup": [
        "SARA-PC         <20> -         M <ACTIVE>  File Server Service",
        "SARA-PC         <00> -         M <ACTIVE>  Workstation Service",
        "GFTECH          <00> - <GROUP> M <ACTIVE>  Domain/Workgroup Name",
        "MAC Address = 38-CA-84-44-5E-58"
    ],
    "smb_dialects": {
        "Supported dialects": {
            "SMB 1.0": false,
            "SMB 2.02": true,
            "SMB 2.1": true,
            "SMB 3.0": true,
            "SMB 3.1.1": true
        },
        "Preferred dialect": "SMB 3.0",
        "SMB1 only": false,
        "SMB signing required": false
    },
    "smb_domain_info": {
        "NetBIOS computer name": "SARA-PC",
        "NetBIOS domain name": "GFTECH",
        "DNS domain": "gftech.srl",
        "FQDN": "sara-pc.gftech.srl",
        "Derived membership": "domain member",
        "Derived domain": "GFTECH"
    },
    "sessions": {
        "sessions_possible": false,
        "null": false,
        "password": false,
        "kerberos": false,
        "nthash": false,
        "random_user": false
    },
    "os_info": {
        "OS": "Windows 10, Windows Server 2019, Windows Server 2016",
        "OS version": "10.0",
        "OS release": "",
        "OS build": "22621",
        "Native OS": "not supported",
        "Native LAN manager": "not supported",
        "Platform id": null,
        "Server type": null,
        "Server type string": null
    },
    "errors": {
        "listeners": {
            "enum_listeners": [
                "Could not connect to LDAP on 389/tcp: timed out",
                "Could not connect to LDAPS on 636/tcp: timed out"
            ]
        },
        "sessions": {
            "enum_sessions": [
                "Could not establish null session: STATUS_ACCESS_DENIED",
                "Could not establish random user session: STATUS_LOGON_FAILURE",
                "Sessions failed, neither null nor user sessions were possible"
            ]
        },
        "os_info": {
            "enum_os_info": [
                "Skipping 'srvinfo' run, not possible with provided credentials"
            ]
        }
    }
}
---
{
    "target": {
        "host": "172.16.1.77"
    },
    "credentials": {
        "auth_method": "null",
        "user": "",
        "password": "",
        "domain": "",
        "ticket_file": "",
        "nthash": "",
        "random_user": "xluvrjbz"
    },
    "listeners": {
        "LDAP": {
            "port": 389,
            "accessible": false
        },
        "LDAPS": {
            "port": 636,
            "accessible": false
        },
        "SMB": {
            "port": 445,
            "accessible": true
        },
        "SMB over NetBIOS": {
            "port": 139,
            "accessible": true
        }
    },
    "domain": "WORKGROUP",
    "nmblookup": [
        "GF-NAS          <00> -         B <ACTIVE>  Workstation Service",
        "GF-NAS          <03> -         B <ACTIVE>  Messenger Service",
        "GF-NAS          <20> -         B <ACTIVE>  File Server Service",
        "WORKGROUP       <00> - <GROUP> B <ACTIVE>  Domain/Workgroup Name",
        "WORKGROUP       <1e> - <GROUP> B <ACTIVE>  Browser Service Elections",
        "MAC Address = 00-00-00-00-00-00"
    ],
    "smb_dialects": {
        "Supported dialects": {
            "SMB 1.0": false,
            "SMB 2.02": true,
            "SMB 2.1": true,
            "SMB 3.0": true,
            "SMB 3.1.1": true
        },
        "Preferred dialect": "SMB 3.0",
        "SMB1 only": false,
        "SMB signing required": false
    },
    "smb_domain_info": {
        "NetBIOS computer name": "GF-NAS",
        "NetBIOS domain name": "",
        "DNS domain": "",
        "FQDN": "gf-nas",
        "Derived membership": "workgroup member",
        "Derived domain": "unknown"
    },
    "sessions": {
        "sessions_possible": false,
        "null": false,
        "password": false,
        "kerberos": false,
        "nthash": false,
        "random_user": false
    },
    "os_info": {
        "OS": "Windows 7, Windows Server 2008 R2",
        "OS version": "6.1",
        "OS release": "",
        "OS build": "0",
        "Native OS": "not supported",
        "Native LAN manager": "not supported",
        "Platform id": null,
        "Server type": null,
        "Server type string": null
    },
    "errors": {
        "listeners": {
            "enum_listeners": [
                "Could not connect to LDAP on 389/tcp: connection refused",
                "Could not connect to LDAPS on 636/tcp: connection refused"
            ]
        },
        "sessions": {
            "enum_sessions": [
                "Could not establish null session: STATUS_ACCESS_DENIED",
                "Could not establish random user session: STATUS_LOGON_FAILURE",
                "Sessions failed, neither null nor user sessions were possible"
            ]
        },
        "os_info": {
            "enum_os_info": [
                "Skipping 'srvinfo' run, not possible with provided credentials"
            ]
        }
    }
}
---
{
    "target": {
        "host": "172.16.1.31"
    },
    "credentials": {
        "auth_method": "null",
        "user": "",
        "password": "",
        "domain": "",
        "ticket_file": "",
        "nthash": "",
        "random_user": "wgswzbug"
    },
    "listeners": {
        "LDAP": {
            "port": 389,
            "accessible": false
        },
        "LDAPS": {
            "port": 636,
            "accessible": false
        },
        "SMB": {
            "port": 445,
            "accessible": true
        },
        "SMB over NetBIOS": {
            "port": 139,
            "accessible": true
        }
    },
    "domain": "WORKGROUP",
    "nmblookup": [
        "GFTECH-NB-CA    <20> -         M <ACTIVE>  File Server Service",
        "GFTECH-NB-CA    <00> -         M <ACTIVE>  Workstation Service",
        "WORKGROUP       <00> - <GROUP> M <ACTIVE>  Domain/Workgroup Name",
        "MAC Address = 60-18-95-49-AA-A6"
    ],
    "smb_dialects": {
        "Supported dialects": {
            "SMB 1.0": false,
            "SMB 2.02": true,
            "SMB 2.1": true,
            "SMB 3.0": true,
            "SMB 3.1.1": true
        },
        "Preferred dialect": "SMB 3.0",
        "SMB1 only": false,
        "SMB signing required": false
    },
    "smb_domain_info": {
        "NetBIOS computer name": "GFTECH-NB-CA",
        "NetBIOS domain name": "",
        "DNS domain": "GFtech-NB-CA",
        "FQDN": "GFtech-NB-CA",
        "Derived membership": "workgroup member",
        "Derived domain": "unknown"
    },
    "sessions": {
        "sessions_possible": false,
        "null": false,
        "password": false,
        "kerberos": false,
        "nthash": false,
        "random_user": false
    },
    "os_info": {
        "OS": "Windows 10, Windows Server 2019, Windows Server 2016",
        "OS version": "10.0",
        "OS release": "2004",
        "OS build": "19041",
        "Native OS": "not supported",
        "Native LAN manager": "not supported",
        "Platform id": null,
        "Server type": null,
        "Server type string": null
    },
    "errors": {
        "listeners": {
            "enum_listeners": [
                "Could not connect to LDAP on 389/tcp: connection refused",
                "Could not connect to LDAPS on 636/tcp: connection refused"
            ]
        },
        "sessions": {
            "enum_sessions": [
                "Could not establish null session: STATUS_ACCESS_DENIED",
                "Could not establish random user session: STATUS_LOGON_FAILURE",
                "Sessions failed, neither null nor user sessions were possible"
            ]
        },
        "os_info": {
            "enum_os_info": [
                "Skipping 'srvinfo' run, not possible with provided credentials"
            ]
        }
    }
}
---
{
    "target": {
        "host": "172.16.1.94"
    },
    "credentials": {
        "auth_method": "null",
        "user": "",
        "password": "",
        "domain": "",
        "ticket_file": "",
        "nthash": "",
        "random_user": "hauxszit"
    },
    "listeners": {
        "LDAP": {
            "port": 389,
            "accessible": false
        },
        "LDAPS": {
            "port": 636,
            "accessible": false
        },
        "SMB": {
            "port": 445,
            "accessible": true
        },
        "SMB over NetBIOS": {
            "port": 139,
            "accessible": true
        }
    },
    "domain": "GFTECH",
    "nmblookup": [
        "GF-PCLUCA       <20> -         M <ACTIVE>  File Server Service",
        "GFTECH          <00> - <GROUP> M <ACTIVE>  Domain/Workgroup Name",
        "GF-PCLUCA       <00> -         M <ACTIVE>  Workstation Service",
        "MAC Address = 30-13-8B-68-6C-41"
    ],
    "smb_dialects": {
        "Supported dialects": {
            "SMB 1.0": false,
            "SMB 2.02": true,
            "SMB 2.1": true,
            "SMB 3.0": true,
            "SMB 3.1.1": true
        },
        "Preferred dialect": "SMB 3.0",
        "SMB1 only": false,
        "SMB signing required": false
    },
    "smb_domain_info": {
        "NetBIOS computer name": "GF-PCLUCA",
        "NetBIOS domain name": "GFTECH",
        "DNS domain": "gftech.srl",
        "FQDN": "GF-PCLUCA.gftech.srl",
        "Derived membership": "domain member",
        "Derived domain": "GFTECH"
    },
    "sessions": {
        "sessions_possible": false,
        "null": false,
        "password": false,
        "kerberos": false,
        "nthash": false,
        "random_user": false
    },
    "os_info": {
        "OS": "Windows 10, Windows Server 2019, Windows Server 2016",
        "OS version": "10.0",
        "OS release": "",
        "OS build": "22621",
        "Native OS": "not supported",
        "Native LAN manager": "not supported",
        "Platform id": null,
        "Server type": null,
        "Server type string": null
    },
    "errors": {
        "listeners": {
            "enum_listeners": [
                "Could not connect to LDAP on 389/tcp: timed out",
                "Could not connect to LDAPS on 636/tcp: timed out"
            ]
        },
        "sessions": {
            "enum_sessions": [
                "Could not establish null session: STATUS_ACCESS_DENIED",
                "Could not establish random user session: STATUS_LOGON_FAILURE",
                "Sessions failed, neither null nor user sessions were possible"
            ]
        },
        "os_info": {
            "enum_os_info": [
                "Skipping 'srvinfo' run, not possible with provided credentials"
            ]
        }
    }
}
---
{
    "target": {
        "host": "172.16.1.110"
    },
    "credentials": {
        "auth_method": "null",
        "user": "",
        "password": "",
        "domain": "",
        "ticket_file": "",
        "nthash": "",
        "random_user": "zfuaozbr"
    },
    "listeners": {
        "LDAP": {
            "port": 389,
            "accessible": false
        },
        "LDAPS": {
            "port": 636,
            "accessible": false
        },
        "SMB": {
            "port": 445,
            "accessible": true
        },
        "SMB over NetBIOS": {
            "port": 139,
            "accessible": true
        }
    },
    "domain": "GFTECH",
    "nmblookup": [
        "GF-CIUCHINO     <00> -         M <ACTIVE>  Workstation Service",
        "GFTECH          <00> - <GROUP> M <ACTIVE>  Domain/Workgroup Name",
        "GF-CIUCHINO     <20> -         M <ACTIVE>  File Server Service",
        "MAC Address = 00-68-EB-AF-A8-40"
    ],
    "smb_dialects": {
        "Supported dialects": {
            "SMB 1.0": false,
            "SMB 2.02": true,
            "SMB 2.1": true,
            "SMB 3.0": true,
            "SMB 3.1.1": true
        },
        "Preferred dialect": "SMB 3.0",
        "SMB1 only": false,
        "SMB signing required": false
    },
    "smb_domain_info": {
        "NetBIOS computer name": "GF-CIUCHINO",
        "NetBIOS domain name": "GFTECH",
        "DNS domain": "gftech.srl",
        "FQDN": "GF-ciuchino.gftech.srl",
        "Derived membership": "domain member",
        "Derived domain": "GFTECH"
    },
    "sessions": {
        "sessions_possible": false,
        "null": false,
        "password": false,
        "kerberos": false,
        "nthash": false,
        "random_user": false
    },
    "os_info": {
        "OS": "Windows 10, Windows Server 2019, Windows Server 2016",
        "OS version": "10.0",
        "OS release": "2004",
        "OS build": "19041",
        "Native OS": "not supported",
        "Native LAN manager": "not supported",
        "Platform id": null,
        "Server type": null,
        "Server type string": null
    },
    "errors": {
        "listeners": {
            "enum_listeners": [
                "Could not connect to LDAP on 389/tcp: connection refused",
                "Could not connect to LDAPS on 636/tcp: connection refused"
            ]
        },
        "sessions": {
            "enum_sessions": [
                "Could not establish null session: STATUS_ACCESS_DENIED",
                "Could not establish random user session: STATUS_LOGON_FAILURE",
                "Sessions failed, neither null nor user sessions were possible"
            ]
        },
        "os_info": {
            "enum_os_info": [
                "Skipping 'srvinfo' run, not possible with provided credentials"
            ]
        }
    }
}
---
{
    "target": {
        "host": "172.16.1.3"
    },
    "credentials": {
        "auth_method": "null",
        "user": "",
        "password": "",
        "domain": "",
        "ticket_file": "",
        "nthash": "",
        "random_user": "jvpvejdn"
    },
    "listeners": {
        "LDAP": {
            "port": 389,
            "accessible": true
        },
        "LDAPS": {
            "port": 636,
            "accessible": true
        },
        "SMB": {
            "port": 445,
            "accessible": true
        },
        "SMB over NetBIOS": {
            "port": 139,
            "accessible": true
        }
    },
    "is_parent_dc": true,
    "is_child_dc": false,
    "long_domain": "gftech.srl",
    "domain": "GFTECH",
    "nmblookup": [
        "GFTECH          <00> - <GROUP> B <ACTIVE>  Domain/Workgroup Name",
        "DC01            <00> -         B <ACTIVE>  Workstation Service",
        "GFTECH          <1c> - <GROUP> B <ACTIVE>  Domain Controllers",
        "DC01            <20> -         B <ACTIVE>  File Server Service",
        "GFTECH          <1b> -         B <ACTIVE>  Domain Master Browser",
        "MAC Address = 00-0C-29-8D-46-02"
    ],
    "smb_dialects": {
        "Supported dialects": {
            "SMB 1.0": true,
            "SMB 2.02": true,
            "SMB 2.1": true,
            "SMB 3.0": true,
            "SMB 3.1.1": true
        },
        "Preferred dialect": "SMB 3.0",
        "SMB1 only": false,
        "SMB signing required": true
    },
    "smb_domain_info": {
        "NetBIOS computer name": "DC01",
        "NetBIOS domain name": "GFTECH",
        "DNS domain": "gftech.srl",
        "FQDN": "DC01.gftech.srl",
        "Derived membership": "domain member",
        "Derived domain": "GFTECH"
    },
    "sessions": {
        "sessions_possible": false,
        "null": false,
        "password": false,
        "kerberos": false,
        "nthash": false,
        "random_user": false
    },
    "os_info": {
        "OS": "Windows Server 2016 Standard 14393",
        "OS version": "10.0",
        "OS release": "1607",
        "OS build": "14393",
        "Native OS": "Windows Server 2016 Standard 14393",
        "Native LAN manager": "Windows Server 2016 Standard 6.3",
        "Platform id": null,
        "Server type": null,
        "Server type string": null
    },
    "errors": {
        "sessions": {
            "enum_sessions": [
                "Could not establish null session: STATUS_ACCESS_DENIED",
                "Could not establish random user session: STATUS_LOGON_FAILURE",
                "Sessions failed, neither null nor user sessions were possible"
            ]
        },
        "os_info": {
            "enum_os_info": [
                "Skipping 'srvinfo' run, not possible with provided credentials"
            ]
        }
    }
}
---
{
    "target": {
        "host": "172.16.1.159"
    },
    "credentials": {
        "auth_method": "null",
        "user": "",
        "password": "",
        "domain": "",
        "ticket_file": "",
        "nthash": "",
        "random_user": "qqdottvk"
    },
    "listeners": {
        "LDAP": {
            "port": 389,
            "accessible": false
        },
        "LDAPS": {
            "port": 636,
            "accessible": false
        },
        "SMB": {
            "port": 445,
            "accessible": true
        },
        "SMB over NetBIOS": {
            "port": 139,
            "accessible": true
        }
    },
    "domain": "GFTECH",
    "nmblookup": [
        "GFTECH-AP       <20> -         M <ACTIVE>  File Server Service",
        "GFTECH-AP       <00> -         M <ACTIVE>  Workstation Service",
        "GFTECH          <00> - <GROUP> M <ACTIVE>  Domain/Workgroup Name",
        "MAC Address = 34-29-8F-10-64-E9"
    ],
    "smb_dialects": {
        "Supported dialects": {
            "SMB 1.0": false,
            "SMB 2.02": true,
            "SMB 2.1": true,
            "SMB 3.0": true,
            "SMB 3.1.1": true
        },
        "Preferred dialect": "SMB 3.0",
        "SMB1 only": false,
        "SMB signing required": false
    },
    "smb_domain_info": {
        "NetBIOS computer name": "GFTECH-AP",
        "NetBIOS domain name": "GFTECH",
        "DNS domain": "gftech.srl",
        "FQDN": "GFTECH-AP.gftech.srl",
        "Derived membership": "domain member",
        "Derived domain": "GFTECH"
    },
    "sessions": {
        "sessions_possible": false,
        "null": false,
        "password": false,
        "kerberos": false,
        "nthash": false,
        "random_user": false
    },
    "os_info": {
        "OS": "Windows 10, Windows Server 2019, Windows Server 2016",
        "OS version": "10.0",
        "OS release": "",
        "OS build": "22621",
        "Native OS": "not supported",
        "Native LAN manager": "not supported",
        "Platform id": null,
        "Server type": null,
        "Server type string": null
    },
    "errors": {
        "listeners": {
            "enum_listeners": [
                "Could not connect to LDAP on 389/tcp: timed out",
                "Could not connect to LDAPS on 636/tcp: timed out"
            ]
        },
        "sessions": {
            "enum_sessions": [
                "Could not establish null session: STATUS_ACCESS_DENIED",
                "Could not establish random user session: STATUS_LOGON_FAILURE",
                "Sessions failed, neither null nor user sessions were possible"
            ]
        },
        "os_info": {
            "enum_os_info": [
                "Skipping 'srvinfo' run, not possible with provided credentials"
            ]
        }
    }
}
---
{
    "target": {
        "host": "172.16.1.131"
    },
    "credentials": {
        "auth_method": "null",
        "user": "",
        "password": "",
        "domain": "",
        "ticket_file": "",
        "nthash": "",
        "random_user": "rfzborzx"
    },
    "listeners": {
        "LDAP": {
            "port": 389,
            "accessible": false
        },
        "LDAPS": {
            "port": 636,
            "accessible": false
        },
        "SMB": {
            "port": 445,
            "accessible": false
        },
        "SMB over NetBIOS": {
            "port": 139,
            "accessible": false
        }
    },
    "domain": null,
    "nmblookup": [
        "MACBOOKAIR-E8D9 <00> -         H <ACTIVE>  Workstation Service",
        "MAC Address = FE-00-71-42-6E-D5"
    ],
    "errors": {
        "listeners": {
            "enum_listeners": [
                "Could not connect to LDAP on 389/tcp: connection refused",
                "Could not connect to LDAPS on 636/tcp: connection refused",
                "Could not connect to SMB on 445/tcp: connection refused",
                "Could not connect to SMB over NetBIOS on 139/tcp: connection refused"
            ]
        },
        "domain": {
            "enum_netbios": [
                "Could not find domain/domain"
            ]
        }
    }
}
---
